dollar/__init__.py
dollar/confighandler.py
dollar/configmap.py
dollar/configtype.py
dollar/dollarcontext.py
dollar/dollarexception.py
dollar/dollarobject.py
dollar/dollarobjectidmap.py
dollar/dollarobjectimpl.py
dollar/builder/__init__.py
dollar/builder/dollarbuilder.py
dollar/builder/dollarlivebuilder.py
dollar/cli/__init__.py
dollar/cli/cli.py
dollar/file/__init__.py
dollar/file/dollarfile.py
dollar/file/dollarfilereader.py
dollar/file/dollarfilewriter.py
dollar/file/filecopier.py
dollar/format/__init__.py
dollar/format/header/__init__.py
dollar/format/header/headerparser.py
dollar/format/header/headerparserresult.py
dollar/format/input/__init__.py
dollar/format/input/inputformat.py
dollar/format/input/inputformattype.py
dollar/format/output/__init__.py
dollar/format/output/outputfactory.py
dollar/format/output/outputformat.py
dollar/format/output/outputformatdollarobjectlinktype.py
dollar/format/output/outputformatter.py
dollar/format/output/outputformatterhandler.py
dollar/format/output/outputformattype.py
dollar/format/raw/__init__.py
dollar/format/raw/rawdollarformat.py
dollar/format/raw/rawdollarformattype.py
dollar/format/raw/rawdollarparser.py
dollar/format/transformer/__init__.py
dollar/format/transformer/headertransformer.py
dollar/format/transformer/inputtostrtransformer.py
dollar/format/transformer/rawtoinputtransformer.py
dollar/helper/__init__.py
dollar/helper/dollarobjectcreationhelper.py
dollar/helper/dollarobjecthelper.py
dollar/helper/validationhelper.py
dollar/plugin/__init__.py
dollar/plugin/builtinpluginloader.py
dollar/plugin/dollarplugin.py
dollar/plugin/pluginarg.py
dollar/plugin/pluginargvalidatior.py
dollar/plugin/pluginhandler.py
dollar/plugin/pluginmap.py
dollar/plugin/plugintype.py
dollar/plugin/builtin/__init__.py
dollar/plugin/builtin/dollarbaseextensionplugin.py
dollar/plugin/builtin/linkfunctionplugin.py
dollar/plugin/builtin/listbacklinksfunctionplugin.py
dollar/plugin/builtin/listfunctionplugin.py
dollardoc-0.4.0.dist-info/LICENSE
dollardoc-0.4.0.dist-info/METADATA
dollardoc-0.4.0.dist-info/WHEEL
dollardoc-0.4.0.dist-info/entry_points.txt
dollardoc-0.4.0.dist-info/top_level.txt
dollardoc-0.4.0.dist-info/RECORD
