Metadata-Version: 2.1
Name: dollardoc
Version: 0.4.0
Summary: Object oriented markdown documentation
Home-page: https://github.com/dollardoc/dollardoc
Author: dollardoc
Author-email: development@dollardoc.dev
License: UNKNOWN
Keywords: documentation,object-oriented,objectoriented,object oriented,markdown,processing,organize,version
Platform: UNKNOWN
Classifier: Development Status :: 2 - Pre-Alpha
Classifier: Intended Audience :: Developers
Classifier: Intended Audience :: Information Technology
Classifier: Intended Audience :: Education
Classifier: Intended Audience :: Science/Research
Classifier: Intended Audience :: System Administrators
Classifier: License :: OSI Approved :: GNU General Public License v3 (GPLv3)
Classifier: Operating System :: OS Independent
Classifier: Programming Language :: Python
Classifier: Programming Language :: Python :: 3.9
Classifier: Topic :: Documentation
Classifier: Topic :: Education
Classifier: Topic :: Office/Business
Classifier: Topic :: Scientific/Engineering
Classifier: Topic :: Software Development
Classifier: Topic :: Software Development :: Documentation
Classifier: Topic :: Software Development :: Version Control
Classifier: Topic :: Text Editors :: Word Processors
Classifier: Topic :: Text Editors :: Text Processing
Classifier: Topic :: Text Processing
Classifier: Topic :: Text Processing :: Markup
Classifier: Topic :: Text Processing :: Markup :: Markdown
Classifier: Topic :: Utilities
Requires-Python: >=3.6
Requires-Dist: PyYAML
